malwi_box/formatting.py
malwi_box/cli.py
malwi_box/toml.py
malwi_box/malwi_box.cpp
malwi_box/hook.py
malwi_box/engine.py
malwi_box/__init__.py
malwi_box/_audit_hook.cpython-311-i386-linux-gnu.so
malwi_box-0.0.11.dist-info/WHEEL
malwi_box-0.0.11.dist-info/entry_points.txt
malwi_box-0.0.11.dist-info/top_level.txt
malwi_box-0.0.11.dist-info/METADATA
malwi_box-0.0.11.dist-info/RECORD
malwi_box-0.0.11.dist-info/licenses/LICENSE.md
