Metadata-Version: 2.4
Name: malwi-box
Version: 0.0.11
Summary: Intercept, audit, and block critical Python operations at runtime
Project-URL: Homepage, https://github.com/canvascomputing/malwi-box
Project-URL: Repository, https://github.com/canvascomputing/malwi-box
Keywords: security,audit,sandbox,malware,python
Classifier: Development Status :: 4 - Beta
Classifier: Intended Audience :: Developers
Classifier: Programming Language :: Python :: 3.10
Classifier: Programming Language :: Python :: 3.11
Classifier: Programming Language :: Python :: 3.12
Classifier: Programming Language :: Python :: 3.13
Classifier: Topic :: Security
Requires-Python: >=3.10
License-File: LICENSE.md
Requires-Dist: pip
Dynamic: license-file
